basedosdados/__init__.py
basedosdados/_version.py
basedosdados/_warnings.py
basedosdados/backend.py
basedosdados/constants.py
basedosdados/core/__init__.py
basedosdados/core/base.py
basedosdados/core/config.toml
basedosdados/download/__init__.py
basedosdados/download/download.py
basedosdados/download/metadata.py
basedosdados/exceptions.py
basedosdados/upload/__init__.py
basedosdados/upload/connection.py
basedosdados/upload/dataset.py
basedosdados/upload/datatypes.py
basedosdados/upload/storage.py
basedosdados/upload/table.py
basedosdados/upload/utils.py
basedosdados-2.0.1.dist-info/METADATA
basedosdados-2.0.1.dist-info/WHEEL
basedosdados-2.0.1.dist-info/RECORD
